Metadata-Version: 2.1
Name: odoo12-addon-stock-card-report
Version: 12.0.1.1.0
Summary: Add stock card report on Inventory Reporting.
Home-page: https://github.com/OCA/stock-logistics-reporting
Author: Ecosoft,Odoo Community Association (OCA)
Author-email: support@odoo-community.org
License: AGPL-3
Platform: UNKNOWN
Classifier: Programming Language :: Python
Classifier: Framework :: Odoo
Classifier: Framework :: Odoo :: 12.0
Classifier: License :: OSI Approved :: GNU Affero General Public License v3
Requires-Python: >=3.5
Requires-Dist: odoo12-addon-date-range
Requires-Dist: odoo12-addon-report-xlsx-helper
Requires-Dist: odoo (<12.1dev,>=12.0a)
